{
  "modules": {
    "byIdentifier": {
      "multi private-next-pages/about.js": 0,
      "multi private-next-pages/index.js": 1,
      "multi next/dist/pages/_app": 2,
      "multi next/dist/pages/_error": 3,
      "multi next/dist/pages/_document": 4
    },
    "usedIds": {
      "0": 0,
      "1": 1,
      "2": 2,
      "3": 3,
      "4": 4
    }
  },
  "chunks": {
    "byName": {
      "init-server.js": 0,
      "on-error-server.js": 1,
      "static\\gJoScaJDbJuGTydXwXDu2\\pages\\_app.js": 2,
      "static\\gJoScaJDbJuGTydXwXDu2\\pages\\_document.js": 3,
      "static\\gJoScaJDbJuGTydXwXDu2\\pages\\_error.js": 4,
      "static\\gJoScaJDbJuGTydXwXDu2\\pages\\about.js": 5,
      "static\\gJoScaJDbJuGTydXwXDu2\\pages\\index.js": 6,
      "static\\oZeC_Q0Xcjxq84JwM0lD6\\pages\\_app.js": 7,
      "static\\oZeC_Q0Xcjxq84JwM0lD6\\pages\\_document.js": 8,
      "static\\oZeC_Q0Xcjxq84JwM0lD6\\pages\\_error.js": 9,
      "static\\oZeC_Q0Xcjxq84JwM0lD6\\pages\\about.js": 10,
      "static\\oZeC_Q0Xcjxq84JwM0lD6\\pages\\index.js": 11,
      "static\\pN0UPS3qaLlEnXI0s5ytg\\pages\\_app.js": 2,
      "static\\pN0UPS3qaLlEnXI0s5ytg\\pages\\_document.js": 3,
      "static\\pN0UPS3qaLlEnXI0s5ytg\\pages\\_error.js": 4,
      "static\\pN0UPS3qaLlEnXI0s5ytg\\pages\\about.js": 5,
      "static\\pN0UPS3qaLlEnXI0s5ytg\\pages\\index.js": 6,
      "static\\-wGuphQe7RH8sC5OqDbxc\\pages\\_app.js": 7,
      "static\\-wGuphQe7RH8sC5OqDbxc\\pages\\_document.js": 8,
      "static\\-wGuphQe7RH8sC5OqDbxc\\pages\\_error.js": 9,
      "static\\-wGuphQe7RH8sC5OqDbxc\\pages\\about.js": 10,
      "static\\-wGuphQe7RH8sC5OqDbxc\\pages\\index.js": 11,
      "static\\-wWay7ovR1x80Mm58g_Zl\\pages\\_app.js": 2,
      "static\\-wWay7ovR1x80Mm58g_Zl\\pages\\_document.js": 3,
      "static\\-wWay7ovR1x80Mm58g_Zl\\pages\\_error.js": 4,
      "static\\-wWay7ovR1x80Mm58g_Zl\\pages\\about.js": 5,
      "static\\-wWay7ovR1x80Mm58g_Zl\\pages\\index.js": 6,
      "static\\gnG3FU0g3xl9ZbDK4Z1cY\\pages\\_app.js": 7,
      "static\\gnG3FU0g3xl9ZbDK4Z1cY\\pages\\_document.js": 8,
      "static\\gnG3FU0g3xl9ZbDK4Z1cY\\pages\\_error.js": 9,
      "static\\gnG3FU0g3xl9ZbDK4Z1cY\\pages\\about.js": 10,
      "static\\gnG3FU0g3xl9ZbDK4Z1cY\\pages\\index.js": 11,
      "static\\7C23oHM4zTrbkYT-l6Y_L\\pages\\_app.js": 2,
      "static\\7C23oHM4zTrbkYT-l6Y_L\\pages\\_document.js": 3,
      "static\\7C23oHM4zTrbkYT-l6Y_L\\pages\\_error.js": 4,
      "static\\7C23oHM4zTrbkYT-l6Y_L\\pages\\about.js": 5,
      "static\\7C23oHM4zTrbkYT-l6Y_L\\pages\\index.js": 6,
      "static\\v7_ICsLm_YDrrSX9u0YJt\\pages\\_app.js": 7,
      "static\\v7_ICsLm_YDrrSX9u0YJt\\pages\\_document.js": 8,
      "static\\v7_ICsLm_YDrrSX9u0YJt\\pages\\_error.js": 9,
      "static\\v7_ICsLm_YDrrSX9u0YJt\\pages\\about.js": 10,
      "static\\v7_ICsLm_YDrrSX9u0YJt\\pages\\index.js": 11,
      "static\\fYeN_f8jTyf87zewl8WW1\\pages\\_app.js": 2,
      "static\\fYeN_f8jTyf87zewl8WW1\\pages\\_document.js": 3,
      "static\\fYeN_f8jTyf87zewl8WW1\\pages\\_error.js": 4,
      "static\\fYeN_f8jTyf87zewl8WW1\\pages\\about.js": 5,
      "static\\fYeN_f8jTyf87zewl8WW1\\pages\\index.js": 6,
      "static\\5kP9n83w_iDls6z7nP7WX\\pages\\_app.js": 7,
      "static\\5kP9n83w_iDls6z7nP7WX\\pages\\_document.js": 8,
      "static\\5kP9n83w_iDls6z7nP7WX\\pages\\_error.js": 9,
      "static\\5kP9n83w_iDls6z7nP7WX\\pages\\about.js": 10,
      "static\\5kP9n83w_iDls6z7nP7WX\\pages\\index.js": 11,
      "static\\XtcL4iQ_QWFL1Xb71raLg\\pages\\_app.js": 2,
      "static\\XtcL4iQ_QWFL1Xb71raLg\\pages\\_document.js": 3,
      "static\\XtcL4iQ_QWFL1Xb71raLg\\pages\\_error.js": 4,
      "static\\XtcL4iQ_QWFL1Xb71raLg\\pages\\about.js": 5,
      "static\\XtcL4iQ_QWFL1Xb71raLg\\pages\\index.js": 6,
      "static\\C-M3HAhV1Lbqve4DF52DW\\pages\\_app.js": 7,
      "static\\C-M3HAhV1Lbqve4DF52DW\\pages\\_document.js": 8,
      "static\\C-M3HAhV1Lbqve4DF52DW\\pages\\_error.js": 9,
      "static\\C-M3HAhV1Lbqve4DF52DW\\pages\\about.js": 10,
      "static\\C-M3HAhV1Lbqve4DF52DW\\pages\\index.js": 11,
      "static\\WDFWUgxkkFqOZBaJTaVIB\\pages\\_app.js": 2,
      "static\\WDFWUgxkkFqOZBaJTaVIB\\pages\\_document.js": 3,
      "static\\WDFWUgxkkFqOZBaJTaVIB\\pages\\_error.js": 4,
      "static\\WDFWUgxkkFqOZBaJTaVIB\\pages\\about.js": 5,
      "static\\WDFWUgxkkFqOZBaJTaVIB\\pages\\index.js": 6,
      "static\\x7-cGFsvuMVnztlRsRlDP\\pages\\_app.js": 7,
      "static\\x7-cGFsvuMVnztlRsRlDP\\pages\\_document.js": 8,
      "static\\x7-cGFsvuMVnztlRsRlDP\\pages\\_error.js": 9,
      "static\\x7-cGFsvuMVnztlRsRlDP\\pages\\about.js": 10,
      "static\\x7-cGFsvuMVnztlRsRlDP\\pages\\index.js": 11
    },
    "bySource": {},
    "usedIds": [
      0,
      1,
      10,
      11,
      7,
      8,
      9
    ]
  }
}